simforge/__init__.py
simforge/baml.py
simforge/client.py
simforge/constants.py
simforge/http.py
simforge/serialize.py
simforge/tracing.py
simforge_py-0.5.0.dist-info/METADATA
simforge_py-0.5.0.dist-info/WHEEL
simforge_py-0.5.0.dist-info/entry_points.txt
simforge_py-0.5.0.dist-info/RECORD
