Metadata-Version: 2.4
Name: simforge-py
Version: 0.5.0
Summary: Simforge client for provider-based API calls with local BAML execution
Author: Harvest Team
Requires-Python: >=3.9
Classifier: Programming Language :: Python :: 3
Classifier: Programming Language :: Python :: 3.9
Classifier: Programming Language :: Python :: 3.10
Classifier: Programming Language :: Python :: 3.11
Classifier: Programming Language :: Python :: 3.12
Classifier: Programming Language :: Python :: 3.13
Classifier: Programming Language :: Python :: 3.14
Provides-Extra: openai-tracing
Requires-Dist: baml-py (>=0.218.0,<0.219.0)
Requires-Dist: jsonpickle (>=4.0.0,<5.0.0)
Requires-Dist: openai-agents (>=0.6.3,<0.7.0) ; extra == "openai-tracing"
Requires-Dist: pydantic (>=2.0.0,<3.0.0)
Requires-Dist: requests (>=2.32.3,<3.0.0)
Requires-Dist: tomli (>=2.0.1,<3.0.0) ; python_version < "3.11"
